Day05__4-bit ALU/alu_4bit.v
module alu_4bit (
    input  [3:0] A,
    input  [3:0] B,
    input  [2:0] ALU_Sel,

    output reg [3:0] Y,
    output reg       Carry
);

always @(*) begin

    Y = 4'b0000;
    Carry = 1'b0;

    case (ALU_Sel)

        
        
        3'b000: begin
            {Carry, Y} = A + B;
        end

        // 001: Subtraction
        3'b001: begin
            Y = A - B;
        end

        // 010: AND
        3'b010: begin
            Y = A & B;
        end

        // 011: OR
        3'b011: begin
            Y = A | B;
        end

        // 100: XOR
        3'b100: begin
            Y = A ^ B;
        end

        // 101: NOT A
        3'b101: begin
            Y = ~A;
        end

        // 110: Left Shift
        3'b110: begin
            Y = A << 1;
        end

        // 111: Right Shift
        3'b111: begin
            Y = A >> 1;
        end

        // Default case
        default: begin
            Y = 4'b0000;
            Carry = 1'b0;
        end

    endcase

end

endmodule

Day05__4-bit ALU/alu_4bit_tb.v
`timescale 1ns/1ps

module alu_4bit_tb;

    // Testbench inputs
    reg [3:0] A;
    reg [3:0] B;
    reg [2:0] ALU_Sel;

    // Testbench outputs
    wire [3:0] Y;
    wire       Carry;

    // Instantiate the ALU
    alu_4bit uut (
        .A(A),
        .B(B),
        .ALU_Sel(ALU_Sel),
        .Y(Y),
        .Carry(Carry)
    );

    // Waveform generation
    initial begin
        $dumpfile("alu.vcd");
        $dumpvars(0, alu_4bit_tb);
    end

    // Test sequence
    initial begin

        // --------------------------------
        // Initial values
        // --------------------------------
        A = 4'b1010;       // 10
        B = 4'b0011;       // 3


        // --------------------------------
        // ADDITION
        // 1010 + 0011 = 1101
        // --------------------------------
        ALU_Sel = 3'b000;
        #10;

        $display("ADD       : A=%b B=%b Y=%b Carry=%b",
                 A, B, Y, Carry);


        // --------------------------------
        // SUBTRACTION
        // 1010 - 0011 = 0111
        // --------------------------------
        ALU_Sel = 3'b001;
        #10;

        $display("SUB       : A=%b B=%b Y=%b",
                 A, B, Y);


        // --------------------------------
        // AND
        // 1010 & 0011 = 0010
        // --------------------------------
        ALU_Sel = 3'b010;
        #10;

        $display("AND       : A=%b B=%b Y=%b",
                 A, B, Y);


        // --------------------------------
        // OR
        // 1010 | 0011 = 1011
        // --------------------------------
        ALU_Sel = 3'b011;
        #10;

        $display("OR        : A=%b B=%b Y=%b",
                 A, B, Y);


        // --------------------------------
        // XOR
        // 1010 ^ 0011 = 1001
        // --------------------------------
        ALU_Sel = 3'b100;
        #10;

        $display("XOR       : A=%b B=%b Y=%b",
                 A, B, Y);


        // --------------------------------
        // NOT
        // ~1010 = 0101
        // --------------------------------
        ALU_Sel = 3'b101;
        #10;

        $display("NOT       : A=%b Y=%b",
                 A, Y);


        // --------------------------------
        // LEFT SHIFT
        // 1010 << 1 = 0100
        // --------------------------------
        ALU_Sel = 3'b110;
        #10;

        $display("LEFT SHIFT: A=%b Y=%b",
                 A, Y);


        // --------------------------------
        // RIGHT SHIFT
        // 1010 >> 1 = 0101
        // --------------------------------
        ALU_Sel = 3'b111;
        #10;

        $display("RIGHT SHIFT: A=%b Y=%b",
                 A, Y);


        // --------------------------------
        // ADDITION OVERFLOW TEST
        // 1111 + 0001 = 1 0000
        // --------------------------------
        A = 4'b1111;
        B = 4'b0001;
        ALU_Sel = 3'b000;
        #10;

        $display("OVERFLOW ADD: A=%b B=%b Y=%b Carry=%b",
                 A, B, Y, Carry);


        // --------------------------------
        // TEST A = 0, B = 0
        // --------------------------------
        A = 4'b0000;
        B = 4'b0000;
        ALU_Sel = 3'b000;
        #10;

        $display("ZERO ADD  : A=%b B=%b Y=%b Carry=%b",
                 A, B, Y, Carry);


        // End simulation
        $finish;

    end

endmodule

Day05__4-bit ALU/alu.vcd
$date
	Sun Aug 09 20:31:28 2026
$end
$version
	Icarus Verilog
$end
$timescale
	1ps
$end
$scope module alu_4bit_tb $end
$var wire 4 ! Y [3:0] $end
$var wire 1 " Carry $end
$var reg 4 # A [3:0] $end
$var reg 3 $ ALU_Sel [2:0] $end
$var reg 4 % B [3:0] $end
$scope module uut $end
$var wire 4 & A [3:0] $end
$var wire 3 ' ALU_Sel [2:0] $end
$var wire 4 ( B [3:0] $end
$var reg 1 " Carry $end
$var reg 4 ) Y [3:0] $end
$upscope $end
$upscope $end
$enddefinitions $end
$comment Show the parameter values. $end
$dumpall
$end
#0
$dumpvars
b1101 )
b11 (
b0 '
b1010 &
b11 %
b0 $
b1010 #
0"
b1101 !
$end
#10000
b111 !
b111 )
b1 $
b1 '
#20000
b10 !
b10 )
b10 $
b10 '
#30000
b1011 !
b1011 )
b11 $
b11 '
#40000
b1001 !
b1001 )
b100 $
b100 '
#50000
b101 !
b101 )
b101 $
b101 '
#60000
b100 !
b100 )
b110 $
b110 '
#70000
b101 !
b101 )
b111 $
b111 '
#80000
1"
b0 !
b0 )
b0 $
b0 '
b1 %
b1 (
b1111 #
b1111 &
#90000
0"
b0 %
b0 (
b0 #
b0 &
