Day03_Multiplexers/mux4to1.v
module mux4to1 (
    input  wire [3:0] i,
    input  wire [1:0] sel,
    output reg y
);

    always @(*) begin
        case (sel)
            2'b00: y = i[0];
            2'b01: y = i[1];
            2'b10: y = i[2];
            2'b11: y = i[3];
            default: y = 1'b0;
        endcase
    end

endmodule

Day03_Multiplexers/mux2to1.v
module mux2to1 (
    input  wire a,
    input  wire b,
    input  wire sel,
    output wire y
);

    assign y = sel ? b : a;

endmodule

Day03_Multiplexers/mux_tb.v
`timescale 1ns/1ps

module mux_tb;

    // -------------------------
    // 2:1 MUX signals
    // -------------------------
    reg a;
    reg b;
    reg sel2;
    wire y2;

    // -------------------------
    // 4:1 MUX signals
    // -------------------------
    reg [3:0] i;
    reg [1:0] sel4;
    wire y4;


    // -------------------------
    // Instantiate 2:1 MUX
    // -------------------------
    mux2to1 M1 (
        .a(a),
        .b(b),
        .sel(sel2),
        .y(y2)
    );


    // -------------------------
    // Instantiate 4:1 MUX
    // -------------------------
    mux4to1 M2 (
        .i(i),
        .sel(sel4),
        .y(y4)
    );


    // -------------------------
    // Test sequence
    // -------------------------
    initial begin

        // Create waveform file
        $dumpfile("waveform.vcd");
        $dumpvars(0, mux_tb);

        // =====================================
        // 2:1 MUX TEST
        // =====================================

        $display("----- 2:1 MUX TEST -----");

        a = 0;
        b = 1;
        sel2 = 0;
        #10;

        a = 0;
        b = 1;
        sel2 = 1;
        #10;

        a = 1;
        b = 0;
        sel2 = 0;
        #10;

        a = 1;
        b = 0;
        sel2 = 1;
        #10;


        // =====================================
        // 4:1 MUX TEST
        // =====================================

        $display("----- 4:1 MUX TEST -----");

        i = 4'b1010;

        sel4 = 2'b00;
        #10;

        sel4 = 2'b01;
        #10;

        sel4 = 2'b10;
        #10;

        sel4 = 2'b11;
        #10;


        $display("Simulation completed.");

        $finish;

    end

endmodule

Day03_Multiplexers/waveform.vcd
$date
	Mon Aug 03 23:35:13 2026
$end
$version
	Icarus Verilog
$end
$timescale
	1ps
$end
$scope module mux_tb $end
$var wire 1 ! y4 $end
$var wire 1 " y2 $end
$var reg 1 # a $end
$var reg 1 $ b $end
$var reg 4 % i [3:0] $end
$var reg 1 & sel2 $end
$var reg 2 ' sel4 [1:0] $end
$scope module M1 $end
$var wire 1 # a $end
$var wire 1 $ b $end
$var wire 1 & sel $end
$var wire 1 " y $end
$upscope $end
$scope module M2 $end
$var wire 4 ( i [3:0] $end
$var wire 2 ) sel [1:0] $end
$var reg 1 ! y $end
$upscope $end
$upscope $end
$enddefinitions $end
$comment Show the parameter values. $end
$dumpall
$end
#0
$dumpvars
bx )
bx (
bx '
0&
bx %
1$
0#
0"
x!
$end
#10000
1"
1&
#20000
0&
0$
1#
#30000
0"
1&
#40000
0!
b0 '
b0 )
b1010 %
b1010 (
#50000
1!
b1 '
b1 )
#60000
0!
b10 '
b10 )
#70000
1!
b11 '
b11 )
